bfabio.pyads-0.1.2.1.dist-info/DESCRIPTION.rst
bfabio.pyads-0.1.2.1.dist-info/METADATA
bfabio.pyads-0.1.2.1.dist-info/RECORD
bfabio.pyads-0.1.2.1.dist-info/WHEEL
bfabio.pyads-0.1.2.1.dist-info/metadata.json
bfabio.pyads-0.1.2.1.dist-info/top_level.txt
pyads/__init__.py
pyads/adsclient.py
pyads/adsconnection.py
pyads/adsdatatype.py
pyads/adsdevice.py
pyads/adsexception.py
pyads/adsio.py
pyads/adsstate.py
pyads/amspacket.py
pyads/binaryparser.py
pyads/procimage.py
pyads/symbolinfo.py
pyads/commands/__init__.py
pyads/commands/adscommand.py
pyads/commands/adsresponse.py
pyads/commands/deviceinfocommand.py
pyads/commands/deviceinforesponse.py
pyads/commands/readcommand.py
pyads/commands/readresponse.py
pyads/commands/readstatecommand.py
pyads/commands/readstateresponse.py
pyads/commands/readwritecommand.py
pyads/commands/readwriteresponse.py
pyads/commands/writecommand.py
pyads/commands/writecontrolcommand.py
pyads/commands/writecontrolresponse.py
pyads/commands/writeresponse.py
